.bumpversion.cfg
.cookiecutterrc
.coveragerc
.editorconfig
.pre-commit-config.yaml
AUTHORS.rst
CHANGELOG.rst
CONTRIBUTING.rst
LICENSE
MANIFEST.in
README.rst
setup.cfg
setup.py
tox.ini
ci/bootstrap.py
ci/requirements.txt
src/batchelor/__init__.py
src/batchelor/main.py
src/batchelor.egg-info/PKG-INFO
src/batchelor.egg-info/SOURCES.txt
src/batchelor.egg-info/dependency_links.txt
src/batchelor.egg-info/not-zip-safe
src/batchelor.egg-info/top_level.txt
tests/test_batchelor.py