Metadata-Version: 1.2
Name: batchelor
Version: 0.5.2
Summary: A simple, yet effective batching system using threadpoolexecutor.
Home-page: https://github.com/ritzKraka/python-batchelor
Author: ritz Kraka
Author-email: ritzKraka@protonmail.com
License: LGPL-3.0-or-later
Project-URL: Changelog, https://github.com/ritzKraka/python-batchelor/blob/master/CHANGELOG.rst
Project-URL: Issue Tracker, https://github.com/ritzKraka/python-batchelor/issues
Keywords: batching,pool,dataset
Platform: UNKNOWN
Classifier: Development Status :: 5 - Production/Stable
Classifier: Intended Audience :: Developers
Classifier: License :: OSI Approved :: GNU General Public License v2 or later (GPLv2+)
Classifier: Operating System :: OS Independent
Classifier: Programming Language :: Python
Classifier: Programming Language :: Python :: 3
Classifier: Programming Language :: Python :: 3.5
Classifier: Programming Language :: Python :: 3.6
Classifier: Programming Language :: Python :: 3.7
Classifier: Programming Language :: Python :: 3.8
Classifier: Topic :: Utilities
Requires-Python: >=3.0
